Workbook

Sheet READ ME FIRST
A1: Target Client List — Rajkot Airport Marketing
A2: 50 prioritized B2B targets for Year 1 outreach
A4: HOW THIS LIST IS BUILT
A5: Segmentation | B5: 5 segments × 10 targets each = 50 high-priority leads to start
A6: Tier | B6: A = top priority (highest budget potential), B = mid, C = volume play
A7: Source | B7: Public-domain research starting points — verify before contact
A9: THE 5 SEGMENTS
A10: 1. Ad Agencies (Gujarat + Mumbai) | B10: Buy media for clients. Best LTV. Highest ticket size. — see TAB 1
A11: 2. National Brands (NRI + Festive) | B11: Direct brand campaigns. Diwali, weddings, summer NRI. — see TAB 2
A12: 3. Regional Brands (Saurashtra/Gujarat) | B12: Local brands going premium. Easier to close. — see TAB 3
A13: 4. Hospitality & Travel | B13: Hotels, tour operators, wedding venues. — see TAB 4
A14: 5. Education, Healthcare & Real Estate | B14: Recurring big spenders in regional markets. — see TAB 5
A16: HOW TO USE THIS FILE
A17: Step 1 | B17: Verify each target — confirm they're active, find current marketing decision-maker
A18: Step 2 | B18: Update 'Last Verified' column with date once confirmed
A19: Step 3 | B19: Use the Status dropdown to track each lead through the funnel
A20: Step 4 | B20: Pipeline Summary tab auto-calculates funnel metrics
A21: Step 5 | B21: Once a target is closed/dead, mark it and refill that slot from Backup Pool tab
A23: STATUS DROPDOWN VALUES
A24: New | B24: Not yet contacted
A25: Verified | B25: Decision-maker identified, contact details confirmed
A26: Outreach Sent | B26: First touch sent (email / WhatsApp / LinkedIn)
A27: Replied | B27: Got a reply, conversation started
A28: Meeting Booked | B28: Demo or pitch call scheduled
A29: Proposal Sent | B29: Custom proposal shared
A30: Negotiating | B30: Active deal discussion
A31: Won | B31: Deal closed, money in
A32: Lost | B32: Said no, with reason logged
A33: Nurture | B33: Not now, follow up in 60-90 days
A35: PRIORITY ORDER FOR FIRST 30 DAYS
A36: Week 1-2 | B36: Verify all 50, focus on Tier A only
A37: Week 3-4 | B37: Outreach to Tier A across all 5 segments (10 targets)
A38: Week 5-6 | B38: Outreach to Tier B (20 targets)
A39: Week 7-8 | B39: Tier C + Backup Pool refresh

Sheet 1. Ad Agencies
A1: Ad Agencies — Gujarat & Mumbai
A2: Media buyers who place ad spend on behalf of clients. Highest LTV segment.
A4: # | B4: Tier | C4: Company / Brand | D4: Why Target | E4: Decision-Maker Role | F4: Where to Find Them | G4: Pitch Angle | H4: Est. Annual Budget Tier | I4: Outreach Channel | J4: Status | K4: Last Verified | L4: Owner | M4: Notes / Next Action
A5: 1 | B5: A | C5: Madison World (Mumbai) | D5: One of India's largest media buying networks; handles brands that target Tier-2 markets; airport OOH is in their regular plan | E5: Media Planner / Group Head — OOH | F5: LinkedIn search 'Madison Media'; madisonworld.com | G5: AAI-partnered exclusive inventory at Rajkot, the Saurashtra-NRI corridor airport — first-mover access to under-tapped Gujarat ad market | H5: Tier A — ₹10L+ | I5: LinkedIn | J5: New | M5: Find OOH planning lead
A6: 2 | B6: A | C6: Lodestar UM / IPG Mediabrands | D6: Major media network; clients spend on regional airport OOH for FMCG and BFSI campaigns | E6: Regional OOH Planner — West | F6: LinkedIn; lodestarum.com | G6: Brand-safe AAI airport, 70-80 screens, dedicated NRI Gujarati audience that BFSI and remittance brands chase | H6: Tier A — ₹10L+ | I6: LinkedIn | J6: New | M6: Target West Region team
A7: 3 | B7: A | C7: GroupM India (Mumbai/Ahmedabad) | D7: Largest media buyer in India by volume; covers Times OOH alternative inventory | E7: Investment Director — OOH / West | F7: LinkedIn; groupm.com | G7: Underpriced Tier-2 airport with premium audience — strong CPM vs Mumbai/Delhi airports for the same NRI/business demographic | H7: Tier A — ₹10L+ | I7: LinkedIn | J7: New | M7: Possible referral via TAFI
A8: 4 | B8: B | C8: Triton Communications (Ahmedabad) | D8: Gujarat-headquartered ad agency, deep regional relationships, regularly buys airport OOH | E8: Account Director / Media Lead | F8: tritoncommunications.in; LinkedIn | G8: Local airport for local agency — strong angle on regional pride and exclusive inventory access | H8: Tier B — ₹3-10L | I8: Email | J8: New | M8: Warm intro via Gujarat business networks
A9: 5 | B9: B | C9: Schbang (Mumbai) | D9: Digital + integrated agency growing OOH practice; clients include challenger brands | E9: OOH / Integrated Media Lead | F9: schbang.com; LinkedIn | G9: Newer airport asset perfect for challenger brands they handle — Instagrammable, story-driven inventory | H9: Tier B — ₹3-10L | I9: LinkedIn | J9: New | M9: Pitch as content+OOH bundle
A10: 6 | B10: B | C10: DDB Mudra Group | D10: Major creative + media network with clients in BFSI, automotive, retail | E10: OOH Planning Lead | F10: ddbmudragroup.com; LinkedIn | G10: Reach Saurashtra business audience (jewelry, ceramics, pharma) at point of arrival/departure | H10: Tier B — ₹3-10L | I10: LinkedIn | J10: New
A11: 7 | B11: B | C11: Wavemaker India | D11: Part of WPP/GroupM, handles big FMCG and auto budgets | E11: Senior Manager — Outdoor | F11: wavemakerglobal.com; LinkedIn | G11: Auto launches and FMCG seasonal pushes — 70-80 screens at Rajkot give 100% visual dominance | H11: Tier B — ₹3-10L | I11: LinkedIn | J11: New
A12: 8 | B12: C | C12: Ogilvy Mumbai (OOH practice) | D12: Premium agency, handles brand campaigns for Indian heritage and luxury brands | E12: OOH / Activation Lead | F12: ogilvy.com; LinkedIn | G12: Wedding-season packages and premium luxury reach for HNI Gujarati audience | H12: Tier C — ₹1-3L | I12: LinkedIn | J12: New
A13: 9 | B13: C | C13: Posterscope India (Dentsu) | D13: Specialist OOH agency, owns relationships with most outdoor inventory in India | E13: Buying Lead — West | F13: posterscope.com; LinkedIn | G13: Be on their inventory roster — single relationship gives access to multiple buying decisions | H13: Tier C — ₹1-3L | I13: Email | J13: New | M13: Long-term relationship play
A14: 10 | B14: C | C14: Laqshya Media Group | D14: OOH and airport media specialist, may treat as competitor or buyer | E14: Business Development | F14: laqshya.com | G14: Sub-license blank inventory to them as wholesale partner if direct sales lag | H14: Tier C — ₹1-3L | I14: Email | J14: New | M14: Backup wholesale option

Sheet 2. National Brands
A1: National Brands — NRI, Travel, Festive Targeting
A2: Brands with national budgets where Saurashtra-NRI audience is a strategic priority.
A4: # | B4: Tier | C4: Company / Brand | D4: Why Target | E4: Decision-Maker Role | F4: Where to Find Them | G4: Pitch Angle | H4: Est. Annual Budget Tier | I4: Outreach Channel | J4: Status | K4: Last Verified | L4: Owner | M4: Notes / Next Action
A5: 1 | B5: A | C5: Western Union India | D5: Targets NRI remittance corridor; Saurashtra has massive UK/US/East Africa Gujarati diaspora | E5: Marketing Head — India / Brand Manager | F5: westernunion.com careers/contact; LinkedIn | G5: Direct catch of returning NRI Gujaratis at moment they're thinking about money transfer | H5: Tier A — ₹10L+ | I5: Email | J5: New | M5: Focus on summer + Diwali return
A6: 2 | B6: A | C6: Wise (formerly TransferWise) | D6: Aggressive challenger to WU/MoneyGram; Indian NRI corridor is priority market | E6: Country Marketing Manager — India | F6: wise.com/careers; LinkedIn | G6: First-mover access to a high-NRI-density airport before competitors lock it down | H6: Tier A — ₹10L+ | I6: Email | J6: New
A7: 3 | B7: A | C7: ICICI Bank — NRI Banking | D7: NRI Gujarati segment is highest-value account holder demographic | E7: AVP — NRI Marketing | F7: icicibank.com; LinkedIn | G7: Welcome-back-to-India campaign at point of arrival — emotional + functional pitch | H7: Tier A — ₹10L+ | I7: Email | J7: New
A8: 4 | B8: A | C8: HDFC Bank — Premier / NRI | D8: Same as ICICI; major NRI banking competitor | E8: Marketing Lead — NRI Services | F8: hdfcbank.com; LinkedIn | G8: Premium NRI audience reach with airport credibility halo | H8: Tier A — ₹10L+ | I8: Email | J8: New
A9: 5 | B9: B | C9: Indigo / Air India / Vistara (codeshares) | D9: Promote new routes, loyalty programs, premium cabins | E9: OOH Marketing Manager | F9: Airline corporate sites; LinkedIn | G9: Cross-promote routes ex-Rajkot — book OOH on the airport you fly to/from | H9: Tier B — ₹3-10L | I9: Email | J9: New
A10: 6 | B10: B | C10: Tata Motors / Mahindra (Auto) | D10: Saurashtra is strong auto market; SUV launches target Tier-2 affluent | E10: Regional Marketing Head — West | F10: tatamotors.com; LinkedIn | G10: Auto launch dominance — full airport takeover packages for new SUV/EV launches | H10: Tier B — ₹3-10L | I10: Email | J10: New
A11: 7 | B11: B | C11: MakeMyTrip / Booking.com | D11: Travel platforms target frequent fliers; airport OOH is on their plan | E11: OOH / Brand Lead | F11: makemytrip.com; booking.com careers | G11: Capture intent — passenger sees ad, books next trip from phone right at airport | H11: Tier B — ₹3-10L | I11: Email | J11: New
A12: 8 | B12: C | C12: Amazon India / Flipkart (Festive) | D12: Diwali, summer, wedding-season pushes are bread and butter | E12: Brand Marketing — Festive | F12: amazon.in / flipkart.com careers | G12: Festive seasonal packages timed to peak NRI return window | H12: Tier C — ₹1-3L | I12: Email | J12: New | M12: Seasonal only
A13: 9 | B13: C | C13: Reliance Jio / Airtel (Roaming) | D13: Roaming and welcome plans for arriving international travelers | E13: Marketing — Roaming/IR | F13: Jio/Airtel corporate sites | G13: Welcome SIM offers right at arrival — high conversion proximity | H13: Tier C — ₹1-3L | I13: Email | J13: New
A14: 10 | B14: C | C14: OYO / Treebo (Hospitality) | D14: Mid-market hospitality targeting domestic + NRI travelers | E14: OOH Marketing | F14: oyorooms.com careers | G14: Bundle with hotel pickup partnerships — dual revenue from hotels + brand | H14: Tier C — ₹1-3L | I14: Email | J14: New

Sheet 3. Regional Brands
A1: Regional Brands — Gujarat & Saurashtra
A2: Local powerhouses with marketing budgets and pride in local presence. Easiest to close.
A4: # | B4: Tier | C4: Company / Brand | D4: Why Target | E4: Decision-Maker Role | F4: Where to Find Them | G4: Pitch Angle | H4: Est. Annual Budget Tier | I4: Outreach Channel | J4: Status | K4: Last Verified | L4: Owner | M4: Notes / Next Action
A5: 1 | B5: A | C5: Balaji Wafers | D5: Gujarat-origin national FMCG brand, regularly does outdoor in home market | E5: Head of Marketing | F5: balajiwafers.com; HQ Rajkot | G5: Hometown airport pride — Balaji on the wall of Rajkot's airport is a no-brainer | H5: Tier A — ₹10L+ | I5: In-Person | J5: New | M5: HQ in Rajkot — direct meeting
A6: 2 | B6: A | C6: Real Diamond / Joyalukkas / Reliance Jewels | D6: Wedding season ads at airport = direct catch of NRI wedding travelers | E6: Regional Marketing Manager — Gujarat | F6: Brand sites; LinkedIn | G6: Wedding season + festive premium — NRIs flying in for family weddings | H6: Tier A — ₹10L+ | I6: Email | J6: New | M6: Peak season Sep-Feb
A7: 3 | B7: A | C7: Cera Sanitaryware / Hindware (Morbi belt) | D7: Morbi is ceramics capital, Cera and Hindware HQ-adjacent, big OOH budgets | E7: Marketing Manager — West | F7: cera-india.com; hindwarehomes.com | G7: Saurashtra business traveler audience — distributors, dealers, builders flying in | H7: Tier A — ₹10L+ | I7: Email | J7: New
A8: 4 | B8: B | C8: Nirma / Saraswati Industrial Syndicate | D8: Gujarat business legacy; corporate brand visibility plays | E8: Corporate Communications | F8: nirma.co.in | G8: Hometown legacy storytelling at Saurashtra's airport gateway | H8: Tier B — ₹3-10L | I8: Email | J8: New
A9: 5 | B9: B | C9: Gujarat Cooperative Milk Marketing (Amul) | D9: National brand, Gujarat heart, regularly does seasonal/regional OOH | E9: Marketing — Brand | F9: amul.com | G9: Festive packages, regional pride angle, easy approval as Gujarat-first brand | H9: Tier B — ₹3-10L | I9: Email | J9: New
A10: 6 | B10: B | C10: Adani Wilmar (Fortune) | D10: FMCG arm, Gujarat HQ, big festive ad spends | E10: Brand Manager | F10: adaniwilmar.com | G10: Festive pushes (Diwali oils, ghee) targeting both NRI and domestic returnees | H10: Tier B — ₹3-10L | I10: Email | J10: New
A11: 7 | B11: B | C11: Torrent Pharma / Zydus Lifesciences | D11: Major Gujarat pharma; OOH for OTC brands and corporate visibility | E11: Brand Marketing | F11: torrentpharma.com; zyduslife.com | G11: OTC brand pushes + corporate visibility for B2B audience flying in | H11: Tier B — ₹3-10L | I11: Email | J11: New
A12: 8 | B12: C | C12: Saffola / Marico (Gujarat retail) | D12: Aggressive on regional festive OOH, especially edible oils | E12: Regional Marketing | F12: marico.com | G12: Festive edible oil push — high relevance to Gujarati household audience | H12: Tier C — ₹1-3L | I12: Email | J12: New
A13: 9 | B13: C | C13: Symphony Cooler (Ahmedabad) | D13: Summer category dominance, Gujarat HQ | E13: Marketing | F13: symphonylimited.com | G13: Summer NRI return + regional summer — perfect timing window | H13: Tier C — ₹1-3L | I13: Email | J13: New | M13: Apr-Jun timing
A14: 10 | B14: C | C14: Havmor / Vadilal Ice Cream | D14: Gujarat heritage F&B brands, summer + festive spends | E14: Marketing Manager | F14: havmor.com; vadilalgroup.com | G14: Summer festive bundle — Gujarat hometown brand visibility | H14: Tier C — ₹1-3L | I14: Email | J14: New

Sheet 4. Hospitality & Travel
A1: Hospitality & Travel — Hotels, Tour Operators, Wedding
A2: Direct partnerships + marketing dollars. Strong cross-sell with meet & greet services.
A4: # | B4: Tier | C4: Company / Brand | D4: Why Target | E4: Decision-Maker Role | F4: Where to Find Them | G4: Pitch Angle | H4: Est. Annual Budget Tier | I4: Outreach Channel | J4: Status | K4: Last Verified | L4: Owner | M4: Notes / Next Action
A5: 1 | B5: A | C5: The Imperial Palace Rajkot | D5: Premium 5★ in Rajkot, NRI wedding venue | E5: GM / Marketing Manager | F5: Direct visit; rajkotpalace.com | G5: Airport-to-hotel branding partnership + meet & greet referral commission | H5: Tier A — ₹10L+ | I5: In-Person | J5: New | M5: Local — Mukesh sir likely knows
A6: 2 | B6: A | C6: Marriott / Hyatt / Radisson Rajkot/Jamnagar | D6: International chains entering Saurashtra wedding market | E6: Director of Marketing | F6: Brand sites; LinkedIn for individual hotels | G6: NRI wedding inbound branding + airport welcome service partnership | H6: Tier A — ₹10L+ | I6: In-Person | J6: New
A7: 3 | B7: A | C7: Inbound Tour Operators — Gujarat (Akbar, Cox & Kings, SOTC) | D7: Sell India-luxury packages to NRIs and international tourists | E7: Regional Manager — West India | F7: Brand sites; TAFI/IATA directories | G7: Premium meet & greet bundled into their tour packages — they earn margin | H7: Tier A — ₹10L+ | I7: Email | J7: New | M7: Recurring revenue model
A8: 4 | B8: B | C8: Wedding Planners — Premium Gujarat (Vivaha, Shaadi Squad, regional) | D8: NRI Gujarati weddings = ₹2-5 crore events; airport meet & greet is standard inclusion | E8: Founder / Operations Head | F8: Instagram, weddingsutra.com directories | G8: VIP guest meet & greet packages with airport experience as premium add-on | H8: Tier B — ₹3-10L | I8: Email | J8: New | M8: Peak Sep-Feb
A9: 5 | B9: B | C9: Statue of Unity / Gujarat Tourism | D9: State tourism push, federal funding available | E9: Tourism Marketing — GTBL | F9: gujarattourism.com | G9: Welcome-to-Gujarat campaign at airport + state tourism partnership | H9: Tier B — ₹3-10L | I9: Email | J9: New | M9: Govt budget cycles
A10: 6 | B10: B | C10: MakeMyTrip / Yatra / Cleartrip (Travel) | D10: Promote tier-2 destination flights and packages | E10: OOH / Brand Lead | F10: makemytrip.com careers; LinkedIn | G10: Drive bookings ex-Rajkot for outbound + inbound; commission on bookings | H10: Tier B — ₹3-10L | I10: Email | J10: New
A11: 7 | B11: C | C11: Lemon Tree / Ginger / Fortune Hotels | D11: Mid-market chains expanding in Saurashtra/Kutch | E11: Regional Marketing | F11: Brand sites; LinkedIn | G11: Affordable airport branding + commission-based meet & greet referrals | H11: Tier C — ₹1-3L | I11: Email | J11: New
A12: 8 | B12: C | C12: Dwarka / Somnath Pilgrimage Operators | D12: Major religious tourism corridor; wealthy pilgrims via Rajkot airport | E12: Senior tour managers | F12: Regional travel agency directories | G12: Premium pilgrim meet & greet packages — captive high-spend audience | H12: Tier C — ₹1-3L | I12: WhatsApp | J12: New
A13: 9 | B13: C | C13: Cruise Operators (Cordelia, etc.) | D13: Mumbai-departure cruises, NRI customer base | E13: Marketing Manager | F13: Brand sites | G13: Targeted reach to high-income leisure travelers | H13: Tier C — ₹1-3L | I13: Email | J13: New
A14: 10 | B14: C | C14: Premium Taxi / Chauffeur Services (Savaari, BlueSmart) | D14: Airport pickup + premium mobility, natural cross-sell | E14: Partnerships Lead | F14: Brand sites | G14: White-label airport pickup partnership + branding revenue | H14: Tier C — ₹1-3L | I14: Email | J14: New

Sheet 5. Edu, Health, Real Estate
A1: Education, Healthcare & Real Estate — High-Value Local
A2: Categories that spend heavily on regional visibility. Real-estate is a sleeper giant.
A4: # | B4: Tier | C4: Company / Brand | D4: Why Target | E4: Decision-Maker Role | F4: Where to Find Them | G4: Pitch Angle | H4: Est. Annual Budget Tier | I4: Outreach Channel | J4: Status | K4: Last Verified | L4: Owner | M4: Notes / Next Action
A5: 1 | B5: A | C5: Marwadi University / RK University Rajkot | D5: NRI student recruitment is key; airport visibility = parents see it | E5: Director — Admissions / Marketing | F5: marwadiuniversity.ac.in; rku.ac.in | G5: Catch parents flying in for admissions; year-round visibility, peak Apr-Jul | H5: Tier A — ₹10L+ | I5: In-Person | J5: New | M5: Local — direct meeting
A6: 2 | B6: A | C6: Sterling Hospital Rajkot / Synergy Hospital | D6: Medical tourism pull, premium healthcare brands chase regional visibility | E6: Marketing Head | F6: sterlinghospitals.com; LinkedIn | G6: Medical tourism inbound + premium positioning for super-specialty services | H6: Tier A — ₹10L+ | I6: Email | J6: New
A7: 3 | B7: A | C7: Apollo / Kokilaben / Jaslok (Mumbai/Gujarat) | D7: Treat Saurashtra region patients; premium medical tourism | E7: Regional Marketing — West | F7: Brand hospital sites; LinkedIn | G7: Capture Saurashtra patients before they default to local options | H7: Tier A — ₹10L+ | I7: Email | J7: New
A8: 4 | B8: B | C8: Real Estate — Adani Realty / Godrej Properties | D8: Major developers with Gujarat projects; OOH is core media plan | E8: Regional Marketing — West Gujarat | F8: Brand sites; LinkedIn | G8: NRI Gujarati real estate buyer — second home / investment property pitch | H8: Tier B — ₹3-10L | I8: Email | J8: New | M8: NRI is the angle
A9: 5 | B9: B | C9: Local Saurashtra Real Estate (Marwadi, Aagam, Jainam) | D9: Regional builders with strong local brand spend | E9: Director / Marketing | F9: Local builder directories; CREDAI Saurashtra | G9: Localized luxury real estate visibility for incoming HNIs and NRIs | H9: Tier B — ₹3-10L | I9: In-Person | J9: New
A10: 6 | B10: B | C10: Coaching Institutes (Allen, Aakash, Resonance, Byju's) | D10: Saurashtra-Kutch is huge JEE/NEET market; parent + student visibility | E10: Regional Marketing | F10: Brand sites; LinkedIn | G10: Admission/result-season campaigns at airport — high parent traffic | H10: Tier B — ₹3-10L | I10: Email | J10: New
A11: 7 | B11: C | C11: Ahmedabad/Vadodara Premier Schools | D11: International schools targeting NRI return families | E11: Admissions Head / Marketing | F11: School websites | G11: Returning NRI parents looking for schools — direct catch at arrival | H11: Tier C — ₹1-3L | I11: Email | J11: New
A12: 8 | B12: C | C12: IVF / Fertility Clinics (Indira IVF, Nova) | D12: Medical tourism + regional patient recruitment | E12: Marketing Director | F12: Brand sites; LinkedIn | G12: Sensitive but high-value category; airport visibility = trust signal | H12: Tier C — ₹1-3L | I12: Email | J12: New
A13: 9 | B13: C | C13: Ayurveda / Wellness Centers (Kerala chains, local) | D13: Wellness tourism corridor | E13: Marketing | F13: Brand sites | G13: Premium wellness inbound traveler reach | H13: Tier C — ₹1-3L | I13: Email | J13: New
A14: 10 | B14: C | C14: Dental / Cosmetic Surgery Clinics | D14: NRI return = medical tourism + cosmetic procedures budget | E14: Practice Marketing Manager | F14: Local listings; Instagram | G14: Capture NRI return medical tourism market | H14: Tier C — ₹1-3L | I14: Email | J14: New

Sheet 📊 Pipeline Summary
A1: Pipeline Summary (Auto-calculated)
A2: Updates automatically as you change Status values in the segment tabs
A4: Status | B4: Ad Agencies | C4: National Brands | D4: Regional Brands | E4: Hospitality & Travel | F4: Edu/Health/Real Estate | G4: TOTAL
A5: New | B5: =COUNTIF('1. Ad Agencies'!J5:J14,"New") -> 10 | C5: =COUNTIF('2. National Brands'!J5:J14,"New") -> 10 | D5: =COUNTIF('3. Regional Brands'!J5:J14,"New") -> 10 | E5: =COUNTIF('4. Hospitality & Travel'!J5:J14,"New") -> 10 | F5: =COUNTIF('5. Edu, Health, Real Estate'!J5:J14,"New") -> 10 | G5: =SUM(B5:F5) -> 50
A6: Verified | B6: =COUNTIF('1. Ad Agencies'!J5:J14,"Verified") -> 0 | C6: =COUNTIF('2. National Brands'!J5:J14,"Verified") -> 0 | D6: =COUNTIF('3. Regional Brands'!J5:J14,"Verified") -> 0 | E6: =COUNTIF('4. Hospitality & Travel'!J5:J14,"Verified") -> 0 | F6: =COUNTIF('5. Edu, Health, Real Estate'!J5:J14,"Verified") -> 0 | G6: =SUM(B6:F6) -> 0
A7: Outreach Sent | B7: =COUNTIF('1. Ad Agencies'!J5:J14,"Outreach Sent") -> 0 | C7: =COUNTIF('2. National Brands'!J5:J14,"Outreach Sent") -> 0 | D7: =COUNTIF('3. Regional Brands'!J5:J14,"Outreach Sent") -> 0 | E7: =COUNTIF('4. Hospitality & Travel'!J5:J14,"Outreach Sent") -> 0 | F7: =COUNTIF('5. Edu, Health, Real Estate'!J5:J14,"Outreach Sent") -> 0 | G7: =SUM(B7:F7) -> 0
A8: Replied | B8: =COUNTIF('1. Ad Agencies'!J5:J14,"Replied") -> 0 | C8: =COUNTIF('2. National Brands'!J5:J14,"Replied") -> 0 | D8: =COUNTIF('3. Regional Brands'!J5:J14,"Replied") -> 0 | E8: =COUNTIF('4. Hospitality & Travel'!J5:J14,"Replied") -> 0 | F8: =COUNTIF('5. Edu, Health, Real Estate'!J5:J14,"Replied") -> 0 | G8: =SUM(B8:F8) -> 0
A9: Meeting Booked | B9: =COUNTIF('1. Ad Agencies'!J5:J14,"Meeting Booked") -> 0 | C9: =COUNTIF('2. National Brands'!J5:J14,"Meeting Booked") -> 0 | D9: =COUNTIF('3. Regional Brands'!J5:J14,"Meeting Booked") -> 0 | E9: =COUNTIF('4. Hospitality & Travel'!J5:J14,"Meeting Booked") -> 0 | F9: =COUNTIF('5. Edu, Health, Real Estate'!J5:J14,"Meeting Booked") -> 0 | G9: =SUM(B9:F9) -> 0
A10: Proposal Sent | B10: =COUNTIF('1. Ad Agencies'!J5:J14,"Proposal Sent") -> 0 | C10: =COUNTIF('2. National Brands'!J5:J14,"Proposal Sent") -> 0 | D10: =COUNTIF('3. Regional Brands'!J5:J14,"Proposal Sent") -> 0 | E10: =COUNTIF('4. Hospitality & Travel'!J5:J14,"Proposal Sent") -> 0 | F10: =COUNTIF('5. Edu, Health, Real Estate'!J5:J14,"Proposal Sent") -> 0 | G10: =SUM(B10:F10) -> 0
A11: Negotiating | B11: =COUNTIF('1. Ad Agencies'!J5:J14,"Negotiating") -> 0 | C11: =COUNTIF('2. National Brands'!J5:J14,"Negotiating") -> 0 | D11: =COUNTIF('3. Regional Brands'!J5:J14,"Negotiating") -> 0 | E11: =COUNTIF('4. Hospitality & Travel'!J5:J14,"Negotiating") -> 0 | F11: =COUNTIF('5. Edu, Health, Real Estate'!J5:J14,"Negotiating") -> 0 | G11: =SUM(B11:F11) -> 0
A12: Won | B12: =COUNTIF('1. Ad Agencies'!J5:J14,"Won") -> 0 | C12: =COUNTIF('2. National Brands'!J5:J14,"Won") -> 0 | D12: =COUNTIF('3. Regional Brands'!J5:J14,"Won") -> 0 | E12: =COUNTIF('4. Hospitality & Travel'!J5:J14,"Won") -> 0 | F12: =COUNTIF('5. Edu, Health, Real Estate'!J5:J14,"Won") -> 0 | G12: =SUM(B12:F12) -> 0
A13: Lost | B13: =COUNTIF('1. Ad Agencies'!J5:J14,"Lost") -> 0 | C13: =COUNTIF('2. National Brands'!J5:J14,"Lost") -> 0 | D13: =COUNTIF('3. Regional Brands'!J5:J14,"Lost") -> 0 | E13: =COUNTIF('4. Hospitality & Travel'!J5:J14,"Lost") -> 0 | F13: =COUNTIF('5. Edu, Health, Real Estate'!J5:J14,"Lost") -> 0 | G13: =SUM(B13:F13) -> 0
A14: Nurture | B14: =COUNTIF('1. Ad Agencies'!J5:J14,"Nurture") -> 0 | C14: =COUNTIF('2. National Brands'!J5:J14,"Nurture") -> 0 | D14: =COUNTIF('3. Regional Brands'!J5:J14,"Nurture") -> 0 | E14: =COUNTIF('4. Hospitality & Travel'!J5:J14,"Nurture") -> 0 | F14: =COUNTIF('5. Edu, Health, Real Estate'!J5:J14,"Nurture") -> 0 | G14: =SUM(B14:F14) -> 0
A15: TOTAL | B15: =SUM(B5:B14) -> 10 | C15: =SUM(C5:C14) -> 10 | D15: =SUM(D5:D14) -> 10 | E15: =SUM(E5:E14) -> 10 | F15: =SUM(F5:F14) -> 10 | G15: =SUM(G5:G14) -> 50
A18: FUNNEL INSIGHTS
A19: Total Targets in System | B19: =SUM(B5:F14) -> 50
A20: Not Yet Contacted | B20: =B5+C5+D5+E5+F5 -> 50
A21: Active Conversations (Replied + Meeting + Proposal + Nego) | B21: =SUM(B8:F11) -> 0
A22: Closed Won | B22: =SUM(B12:F12) -> 0
A23: Closed Lost | B23: =SUM(B13:F13) -> 0
A24: Reply Rate (vs Outreach Sent) | B24: =IF(SUM(B7:F7)+SUM(B8:F8)+SUM(B9:F9)+SUM(B10:F10)+SUM(B11:F11)+SUM(B12:F12)+SUM(B13:F13)=0,0,(SUM(B8:F8)+SUM(B9:F9)+SUM(B10:F10)+SUM(B11:F11)+SUM(B12:F12)+SUM(B13:F13))/(SUM(B7:F7)+SUM(B8:F8)+SUM(B9:F9)+SUM(B10:F10)+SUM(B11:F11)+SUM(B12:F12)+SUM(B13:F13))) -> 0
A25: Win Rate (Won vs Won+Lost) | B25: =IF(SUM(B12:F12)+SUM(B13:F13)=0,0,SUM(B12:F12)/(SUM(B12:F12)+SUM(B13:F13))) -> 0

Sheet Backup Pool
A1: Backup Pool — Refill Slots as Targets Close/Die
A2: 30 additional verified-direction targets to draw from when primary list slots open up.
A4: # | B4: Segment | C4: Company / Brand | D4: Why Worth Pursuing | E4: Tier | F4: Notes
A5: 1 | B5: Ad Agency | C5: Initiative Media (IPG) | D5: Major media network, OOH practice | E5: B
A6: 2 | B6: Ad Agency | C6: Mindshare India | D6: WPP/GroupM, big budgets | E6: B
A7: 3 | B7: Ad Agency | C7: Havas Media India | D7: Growing OOH practice | E7: C
A8: 4 | B8: Ad Agency | C8: Carat India | D8: Dentsu media network | E8: C
A9: 5 | B9: Ad Agency | C9: Milestone Brandcom (Mumbai) | D9: Specialist OOH agency | E9: C
A10: 6 | B10: National Brand | C10: MoneyGram India | D10: NRI remittance — same play as Western Union | E10: B
A11: 7 | B11: National Brand | C11: Remitly / Xoom (PayPal) | D11: NRI remittance challengers | E11: B
A12: 8 | B12: National Brand | C12: SBI NRI Services | D12: Massive NRI customer base | E12: B
A13: 9 | B13: National Brand | C13: Axis Bank Burgundy / Privée | D13: Premium banking for HNIs | E13: B
A14: 10 | B14: National Brand | C14: Tanishq / Kalyan Jewellers | D14: Wedding + festive jewelry | E14: A | F14: Could move to primary
A15: 11 | B15: National Brand | C15: Asian Paints / Berger (Festive) | D15: Festive home renovation push | E15: C
A16: 12 | B16: National Brand | C16: ITC Hotels / Welcomgroup | D16: Premium domestic hospitality | E16: B
A17: 13 | B17: Regional | C17: Ajanta-Orpat (Morbi clocks/electricals) | D17: Local industry, regional pride angle | E17: C
A18: 14 | B18: Regional | C18: Astral Pipes (Ahmedabad) | D18: Big Gujarat brand, plumbing + adhesives | E18: B
A19: 15 | B19: Regional | C19: Suzlon Energy (Pune/Gujarat) | D19: Wind energy; corporate visibility play | E19: C
A20: 16 | B20: Regional | C20: Patel Group / Kalupur Bank | D20: Local financial brands | E20: C
A21: 17 | B21: Regional | C21: Gokul / Madhur Industries | D21: Edible oils, Gujarat heritage | E21: C
A22: 18 | B22: Hospitality | C22: Le Meridien / ITC Narmada | D22: Premium chains in Ahmedabad/Vadodara | E22: B
A23: 19 | B23: Hospitality | C23: Thomas Cook India | D23: Inbound + outbound packages | E23: B
A24: 20 | B24: Hospitality | C24: Veena World / Kesari Tours | D24: Indian-origin tour operators | E24: C
A25: 21 | B25: Hospitality | C25: Airbnb India (Premium Plus) | D25: Targeting high-end Indian leisure travel | E25: C
A26: 22 | B26: Healthcare | C26: Sankara Eye / Aravind | D26: Medical tourism, cataract specialty | E26: B
... A28: 24 | B28: Healthcare | C28: Practo / Tata 1mg | D28: Healthcare digital platforms | E28: C
A29: 25 | B29: Education | C29: BITS Pilani / IIM Ahmedabad | D29: Premium education brands | E29: B | F29: B-school exec MBA targeting
A30: 26 | B30: Education | C30: NIIT / Aptech | D30: Tech education, regional targeting | E30: C
A31: 27 | B31: Real Estate | C31: DLF / Brigade Group | D31: National developers with Gujarat plays | E31: B
A32: 28 | B32: Real Estate | C32: Sobha / Prestige | D32: Premium developers | E32: C
A33: 29 | B33: Auto | C33: Maruti / Hyundai (Regional) | D33: Auto launches, regional targeting | E33: B
A34: 30 | B34: Auto | C34: TVS / Bajaj Auto | D34: Two-wheeler regional pushes | E34: C
